{"bio": "Robert joined Tableau in 2012 to drive product innovations that help the average business user visualize their data.  Robert has always been fascinated by the art of visualization and organization of large data.  He spent many years with Silicon Graphics creating large data visualization solutions and partnerships.  Robert also worked for Intel (McAfee division) leading the product team\u2019s efforts to build consumer security software for PC manufacturers.   In his spare time, Robert enjoys tinkering with new technologies (specifically around home automation), drinking good wine and discussing the \u201cwhat-if\u201d questions that spur innovation for visual analytics.", "name": "Robert Green", "title": "Director of Product Management, Technology Partners ", "id": 2, "affiliation": "Tableau Software", "type": "speaker", "email": ""}